psp/__init__.py
psp/clients/island/scripts/import_forecast_history.py
psp/clients/island/scripts/import_poc_hourly_data.py
psp/clients/mone/scripts/parse_poc_data.py
psp/clients/mone/scripts/resample_pv_data_5min.py
psp/clients/sme/parse_poc_data_sme.py
psp/clients/uk_pv/README.md
psp/clients/uk_pv/data.py
psp/clients/uk_pv/scripts/data_to_netcdf.py
psp/clients/uk_pv/scripts/simplify_data.py
psp/data_sources/__init__.py
psp/data_sources/nwp.py
psp/data_sources/pv.py
psp/data_sources/satellite.py
psp/data_sources/utils.py
psp/dataset.py
psp/exp_configs/__init__.py
psp/exp_configs/base.py
psp/exp_configs/island.py
psp/exp_configs/island_historical_forecasts.py
psp/exp_configs/mone.py
psp/exp_configs/mone_yesterday.py
psp/exp_configs/sme.py
psp/exp_configs/sme_yesterday.py
psp/exp_configs/test_config1.py
psp/exp_configs/uk_pv.py
psp/exp_configs/uk_pv_prod.py
psp/exp_configs/uk_pv_site_comp.py
psp/exp_configs/uk_pv_site_comp_gen.py
psp/exp_configs/yesterday.py
psp/gis.py
psp/metrics.py
psp/models/README.md
psp/models/__init__.py
psp/models/base.py
psp/models/historical_forecasts.py
psp/models/multi.py
psp/models/recent_history.py
psp/models/regressors/base.py
psp/models/regressors/decision_trees.py
psp/models/regressors/neural_net.py
psp/models/yesterday.py
psp/pv.py
psp/py.typed
psp/scripts/_options.py
psp/scripts/eval_model.py
psp/scripts/infer_pv_metadata.py
psp/scripts/inspect_data_file.py
psp/scripts/train_model.py
psp/serialization.py
psp/testing.py
psp/tests/clients/uk_pv/test_data.py
psp/tests/conftest.py
psp/tests/data/data_sources/test_nwp_data_source.py
psp/tests/data/data_sources/test_pv_data_source.py
psp/tests/data/data_sources/test_satellite_data_source.py
psp/tests/data/data_sources/test_utils.py
psp/tests/fixtures/README.md
psp/tests/fixtures/models/README.md
psp/tests/fixtures/models/model_v8.pkl
psp/tests/fixtures/models/model_v9.pkl
psp/tests/fixtures/nwp.zarr/.zattrs
psp/tests/fixtures/nwp.zarr/.zgroup
psp/tests/fixtures/nwp.zarr/.zmetadata
pv_site_prediction-0.1.20.dist-info/METADATA
pv_site_prediction-0.1.20.dist-info/WHEEL
pv_site_prediction-0.1.20.dist-info/RECORD
