Metadata-Version: 2.1
Name: pv-site-prediction
Version: 0.1.20
Summary: Photovoltaic per site modeling
License: MIT
Author: Simon Lemieux
Author-email: 1105380+simlmx@users.noreply.github.com
Requires-Python: >=3.10,<3.12
Classifier: License :: OSI Approved :: MIT License
Classifier: Programming Language :: Python :: 3
Classifier: Programming Language :: Python :: 3.10
Classifier: Programming Language :: Python :: 3.11
Provides-Extra: torch
Requires-Dist: click (>=8.1.3,<9.0.0)
Requires-Dist: dask (>=2022.12.1,<2023.0.0)
Requires-Dist: fsspec (>=2022.11.0,<2023.0.0)
Requires-Dist: gcsfs (>=2022.11.0,<2023.0.0)
Requires-Dist: google-cloud-storage (>=2.7.0,<3.0.0)
Requires-Dist: h5netcdf (>=1.1.0,<2.0.0)
Requires-Dist: netcdf4 (>=1.6.3,<2.0.0)
Requires-Dist: numpy (==1.23.5)
Requires-Dist: ocf-blosc2 (>=0.0.2,<0.0.3)
Requires-Dist: pvlib (>=0.9.3,<0.10.0)
Requires-Dist: pyproj (>=3.4.1,<4.0.0)
Requires-Dist: pyresample (>=1.27.1,<2.0.0)
Requires-Dist: scikit-learn (>=1.1.3,<1.2.0)
Requires-Dist: torch (>=1.13.1,<2.0.0) ; extra == "torch"
Requires-Dist: tqdm (>=4.64.1,<5.0.0)
Requires-Dist: xarray (>=2022.12.0,<2023.0.0)
Requires-Dist: zarr (>=2.13.3,<3.0.0)
